bflag/__init__.py
bflag/_modidx.py
bflag/bflag.py
bflag/butil.py
bflag/core.py
bflag/flags.py
bflag/futil.py
bflag/inst.py
bflag/types.py
bflag-0.0.9.dist-info/LICENSE
bflag-0.0.9.dist-info/METADATA
bflag-0.0.9.dist-info/WHEEL
bflag-0.0.9.dist-info/entry_points.txt
bflag-0.0.9.dist-info/top_level.txt
bflag-0.0.9.dist-info/RECORD
