Metadata-Version: 2.1
Name: bflag
Version: 0.0.9
Summary: si type metric
Home-page: https://github.com/dsm-72/bflag
Author: dsm-72
Author-email: sumner.magruder@yale.edu
License: Apache Software License 2.0
Keywords: python bool flag bflag boolean flag fool booly boolish
Classifier: Development Status :: 4 - Beta
Classifier: Intended Audience :: Developers
Classifier: Natural Language :: English
Classifier: Programming Language :: Python :: 3.11
Classifier: License :: OSI Approved :: Apache Software License
Requires-Python: >=3.11
License-File: LICENSE
Requires-Dist: atyp
Requires-Dist: chck
Requires-Dist: nchr
Requires-Dist: nlit
Provides-Extra: dev
